pgnsplit/__init__.py
pgnsplit/main.py
pgnsplit/pgn_splitter.py
pgnsplit-0.1.2.dist-info/entry_points.txt
pgnsplit-0.1.2.dist-info/LICENSE
pgnsplit-0.1.2.dist-info/WHEEL
pgnsplit-0.1.2.dist-info/METADATA
pgnsplit-0.1.2.dist-info/RECORD
