Metadata-Version: 2.1
Name: pgnsplit
Version: 0.1.2
Summary: Simple package that splits a chess pgn file into a folder of pgns - each one containing one variation of the original pgn.
Home-page: https://github.com/vsingh18567/pgn-split
License: MIT
Keywords: Chess,CLI,PGN
Author: vsingh18567
Author-email: vsingh18567@gmail.com
Requires-Python: >=3.8,<4.0
Classifier: License :: OSI Approved :: MIT License
Classifier: Programming Language :: Python :: 3
Classifier: Programming Language :: Python :: 3.8
Classifier: Programming Language :: Python :: 3.9
Requires-Dist: chess (>=1.6.1,<2.0.0)
Requires-Dist: click (>=8.0.1,<9.0.0)
Project-URL: Repository, https://github.com/vsingh18567/pgn-split
